{
  "type": "GROUP",
"name": "Global Information",
"path": "",
"pathFormatted": "group_missing-name-b06d1",
"stats": {
    "name": "Global Information",
    "numberOfRequests": {
        "total": 7963,
        "ok": 7936,
        "ko": 27
    },
    "minResponseTime": {
        "total": 0,
        "ok": 45,
        "ko": 0
    },
    "maxResponseTime": {
        "total": 8035,
        "ok": 8035,
        "ko": 559
    },
    "meanResponseTime": {
        "total": 361,
        "ok": 361,
        "ko": 204
    },
    "standardDeviation": {
        "total": 330,
        "ok": 330,
        "ko": 127
    },
    "percentiles1": {
        "total": 259,
        "ok": 259,
        "ko": 184
    },
    "percentiles2": {
        "total": 528,
        "ok": 529,
        "ko": 264
    },
    "percentiles3": {
        "total": 976,
        "ok": 977,
        "ko": 465
    },
    "percentiles4": {
        "total": 1400,
        "ok": 1400,
        "ko": 548
    },
    "group1": {
        "name": "t < 800 ms",
        "count": 7199,
        "percentage": 90
    },
    "group2": {
        "name": "800 ms < t < 1200 ms",
        "count": 538,
        "percentage": 7
    },
    "group3": {
        "name": "t > 1200 ms",
        "count": 199,
        "percentage": 2
    },
    "group4": {
        "name": "failed",
        "count": 27,
        "percentage": 0
    },
    "meanNumberOfRequestsPerSecond": {
        "total": 107.60810810810811,
        "ok": 107.24324324324324,
        "ko": 0.36486486486486486
    }
},
"contents": {
"req_initiate-88167": {
        "type": "REQUEST",
        "name": "Initiate",
"path": "Initiate",
"pathFormatted": "req_initiate-88167",
"stats": {
    "name": "Initiate",
    "numberOfRequests": {
        "total": 2000,
        "ok": 1993,
        "ko": 7
    },
    "minResponseTime": {
        "total": 0,
        "ok": 184,
        "ko": 0
    },
    "maxResponseTime": {
        "total": 8035,
        "ok": 8035,
        "ko": 343
    },
    "meanResponseTime": {
        "total": 627,
        "ok": 628,
        "ko": 177
    },
    "standardDeviation": {
        "total": 391,
        "ok": 391,
        "ko": 126
    },
    "percentiles1": {
        "total": 553,
        "ok": 554,
        "ko": 218
    },
    "percentiles2": {
        "total": 781,
        "ok": 782,
        "ko": 268
    },
    "percentiles3": {
        "total": 1341,
        "ok": 1341,
        "ko": 327
    },
    "percentiles4": {
        "total": 1859,
        "ok": 1861,
        "ko": 340
    },
    "group1": {
        "name": "t < 800 ms",
        "count": 1526,
        "percentage": 76
    },
    "group2": {
        "name": "800 ms < t < 1200 ms",
        "count": 312,
        "percentage": 16
    },
    "group3": {
        "name": "t > 1200 ms",
        "count": 155,
        "percentage": 8
    },
    "group4": {
        "name": "failed",
        "count": 7,
        "percentage": 0
    },
    "meanNumberOfRequestsPerSecond": {
        "total": 27.027027027027028,
        "ok": 26.93243243243243,
        "ko": 0.0945945945945946
    }
}
    },"req_welcome-83218": {
        "type": "REQUEST",
        "name": "Welcome",
"path": "Welcome",
"pathFormatted": "req_welcome-83218",
"stats": {
    "name": "Welcome",
    "numberOfRequests": {
        "total": 1993,
        "ok": 1991,
        "ko": 2
    },
    "minResponseTime": {
        "total": 45,
        "ok": 45,
        "ko": 163
    },
    "maxResponseTime": {
        "total": 1391,
        "ok": 1391,
        "ko": 265
    },
    "meanResponseTime": {
        "total": 138,
        "ok": 138,
        "ko": 214
    },
    "standardDeviation": {
        "total": 152,
        "ok": 152,
        "ko": 51
    },
    "percentiles1": {
        "total": 75,
        "ok": 75,
        "ko": 214
    },
    "percentiles2": {
        "total": 137,
        "ok": 137,
        "ko": 240
    },
    "percentiles3": {
        "total": 480,
        "ok": 480,
        "ko": 260
    },
    "percentiles4": {
        "total": 776,
        "ok": 776,
        "ko": 264
    },
    "group1": {
        "name": "t < 800 ms",
        "count": 1973,
        "percentage": 99
    },
    "group2": {
        "name": "800 ms < t < 1200 ms",
        "count": 17,
        "percentage": 1
    },
    "group3": {
        "name": "t > 1200 ms",
        "count": 1,
        "percentage": 0
    },
    "group4": {
        "name": "failed",
        "count": 2,
        "percentage": 0
    },
    "meanNumberOfRequestsPerSecond": {
        "total": 26.93243243243243,
        "ok": 26.905405405405407,
        "ko": 0.02702702702702703
    }
}
    },"req_content-f15c1": {
        "type": "REQUEST",
        "name": "Content",
"path": "Content",
"pathFormatted": "req_content-f15c1",
"stats": {
    "name": "Content",
    "numberOfRequests": {
        "total": 1991,
        "ok": 1979,
        "ko": 12
    },
    "minResponseTime": {
        "total": 58,
        "ok": 96,
        "ko": 58
    },
    "maxResponseTime": {
        "total": 1563,
        "ok": 1563,
        "ko": 559
    },
    "meanResponseTime": {
        "total": 469,
        "ok": 470,
        "ko": 190
    },
    "standardDeviation": {
        "total": 265,
        "ok": 264,
        "ko": 123
    },
    "percentiles1": {
        "total": 428,
        "ok": 429,
        "ko": 167
    },
    "percentiles2": {
        "total": 606,
        "ok": 607,
        "ko": 191
    },
    "percentiles3": {
        "total": 983,
        "ok": 985,
        "ko": 396
    },
    "percentiles4": {
        "total": 1304,
        "ok": 1304,
        "ko": 526
    },
    "group1": {
        "name": "t < 800 ms",
        "count": 1771,
        "percentage": 89
    },
    "group2": {
        "name": "800 ms < t < 1200 ms",
        "count": 166,
        "percentage": 8
    },
    "group3": {
        "name": "t > 1200 ms",
        "count": 42,
        "percentage": 2
    },
    "group4": {
        "name": "failed",
        "count": 12,
        "percentage": 1
    },
    "meanNumberOfRequestsPerSecond": {
        "total": 26.905405405405407,
        "ok": 26.743243243243242,
        "ko": 0.16216216216216217
    }
}
    },"req_response-d64ed": {
        "type": "REQUEST",
        "name": "Response",
"path": "Response",
"pathFormatted": "req_response-d64ed",
"stats": {
    "name": "Response",
    "numberOfRequests": {
        "total": 1979,
        "ok": 1973,
        "ko": 6
    },
    "minResponseTime": {
        "total": 55,
        "ok": 55,
        "ko": 68
    },
    "maxResponseTime": {
        "total": 1311,
        "ok": 1311,
        "ko": 518
    },
    "meanResponseTime": {
        "total": 208,
        "ok": 208,
        "ko": 259
    },
    "standardDeviation": {
        "total": 182,
        "ok": 182,
        "ko": 138
    },
    "percentiles1": {
        "total": 143,
        "ok": 143,
        "ko": 244
    },
    "percentiles2": {
        "total": 243,
        "ok": 242,
        "ko": 293
    },
    "percentiles3": {
        "total": 611,
        "ok": 612,
        "ko": 462
    },
    "percentiles4": {
        "total": 919,
        "ok": 919,
        "ko": 507
    },
    "group1": {
        "name": "t < 800 ms",
        "count": 1929,
        "percentage": 97
    },
    "group2": {
        "name": "800 ms < t < 1200 ms",
        "count": 43,
        "percentage": 2
    },
    "group3": {
        "name": "t > 1200 ms",
        "count": 1,
        "percentage": 0
    },
    "group4": {
        "name": "failed",
        "count": 6,
        "percentage": 0
    },
    "meanNumberOfRequestsPerSecond": {
        "total": 26.743243243243242,
        "ok": 26.66216216216216,
        "ko": 0.08108108108108109
    }
}
    }
}

}